README.md
setup.py
lmrun/__init__.py
lmrun/lmrun.py
lmrun.egg-info/PKG-INFO
lmrun.egg-info/SOURCES.txt
lmrun.egg-info/dependency_links.txt
lmrun.egg-info/entry_points.txt
lmrun.egg-info/requires.txt
lmrun.egg-info/top_level.txt