Metadata-Version: 2.1
Name: lmrun
Version: 0.0.6
Summary: A CLI to run Groovy or PowerShell scripts on a LogicMonitor collector for debugging purposes
Home-page: UNKNOWN
Author: Max Anderson
Author-email: <cctpmax@gmail.com>
License: UNKNOWN
Project-URL: GitHub, https://github.com/MaxAnderson95/lmrun
Keywords: logicmonitor,cli
Platform: UNKNOWN
Classifier: Development Status :: 1 - Planning
Classifier: Intended Audience :: Developers
Classifier: Programming Language :: Python :: 3
Classifier: Operating System :: Unix
Classifier: Operating System :: MacOS :: MacOS X
Classifier: Operating System :: Microsoft :: Windows
